wizwalker/extensions/wizsprinter/__init__.py
wizwalker/extensions/wizsprinter/combat_lifting.py
wizwalker/extensions/wizsprinter/sprinty_client.py
wizwalker/extensions/wizsprinter/sprinty_combat.py
wizwalker/extensions/wizsprinter/wiz_navigator.py
wizwalker/extensions/wizsprinter/wiz_sprinter.py
wizwalker/extensions/wizsprinter/combat_backends/backend_base.py
wizwalker/extensions/wizsprinter/combat_backends/combat_api.py
wizwalker/extensions/wizsprinter/combat_backends/combat_config_parser.py
wizwalker/extensions/wizsprinter/combat_backends/config_backend.py
wizwalker/extensions/wizsprinter/combat_backends/generator_backend.py
wizwalker/extensions/wizsprinter/traversalData/gates_list.txt
wizwalker/extensions/wizsprinter/traversalData/interactiveTeleporters.txt
wizwalker/extensions/wizsprinter/traversalData/objectLocations.txt
wizwalker/extensions/wizsprinter/traversalData/uniqueObjectLocations.txt
wizwalker/extensions/wizsprinter/traversalData/zoneMap.txt
wizsprinter-0.6.2.dist-info/LICENSE
wizsprinter-0.6.2.dist-info/METADATA
wizsprinter-0.6.2.dist-info/WHEEL
wizsprinter-0.6.2.dist-info/top_level.txt
wizsprinter-0.6.2.dist-info/RECORD
