Metadata-Version: 2.1
Name: wizsprinter
Version: 0.6.2
Summary: A semi-official WizWalker extension
Home-page: UNKNOWN
Author: SirOlaf
Maintainer: CowHunter0
Maintainer-email: cowhunter04@gmail.com
License: UNKNOWN
Platform: UNKNOWN
Requires-Python: >=3.8,<4.0
License-File: LICENSE
Requires-Dist: lark (<0.12.0,>=0.11.3)
Requires-Dist: wizwalker (>=1.0.0)
